GopaleshTopsis/__init__.py
GopaleshTopsis/utils.py
GopaleshTopsis-0.1.7.dist-info/METADATA
GopaleshTopsis-0.1.7.dist-info/WHEEL
GopaleshTopsis-0.1.7.dist-info/top_level.txt
GopaleshTopsis-0.1.7.dist-info/RECORD
